terseparse/__init__.py
terseparse/builders.py
terseparse/root_parser.py
terseparse/types.py
terseparse/utils.py
terseparse/version.py
terseparse-1.3.1.dist-info/METADATA
terseparse-1.3.1.dist-info/WHEEL
terseparse-1.3.1.dist-info/top_level.txt
terseparse-1.3.1.dist-info/RECORD
